LICENSE.txt
MANIFEST.in
README.md
pyproject.toml
requirements.txt
setup.cfg
setup.py
BinaryFileReader/HexaReader.py
BinaryFileReader/MagicStrings.py
BinaryFileReader/Strings.py
BinaryFileReader/__init__.py
BinaryFileReader/__main__.py
BinaryFileReader.egg-info/PKG-INFO
BinaryFileReader.egg-info/SOURCES.txt
BinaryFileReader.egg-info/dependency_links.txt
BinaryFileReader.egg-info/entry_points.txt
BinaryFileReader.egg-info/requires.txt
BinaryFileReader.egg-info/top_level.txt