Metadata-Version: 2.2
Name: BinaryFileReader
Version: 3.0.4
Summary: This package reads binary file to exports strings or prints content as hexadecimal.
Home-page: https://github.com/mauricelambert/BinaryFileReader
Download-URL: https://mauricelambert.github.io/info/python/security/BinaryFileReader/BinaryFileReader.pyz
Author: Maurice Lambert
Author-email: Maurice Lambert <mauricelambert434@gmail.com>
Maintainer: Maurice Lambert
Maintainer-email: Maurice Lambert <mauricelambert434@gmail.com>
License: GPL-3.0 License
Project-URL: Github, https://github.com/mauricelambert/BinaryFileReader
Project-URL: Strings Documentation, https://mauricelambert.github.io/info/python/security/BinaryFileReader/Strings.html
Project-URL: Strings Python Executable, https://mauricelambert.github.io/info/python/security/BinaryFileReader/Strings.pyz
Project-URL: Strings Windows Executable, https://mauricelambert.github.io/info/python/security/BinaryFileReader/Strings.exe
Project-URL: HexaReader Documentation, https://mauricelambert.github.io/info/python/security/BinaryFileReader/HexaReader.html
Project-URL: HexaReader Python Executable, https://mauricelambert.github.io/info/python/security/BinaryFileReader/HexaReader.pyz
Project-URL: HexaReader Windows Executable, https://mauricelambert.github.io/info/python/security/BinaryFileReader/HexaReader.exe
Project-URL: MagicStrings Documentation, https://mauricelambert.github.io/info/python/security/BinaryFileReader/MagicStrings.html
Project-URL: MagicStrings Python Executable, https://mauricelambert.github.io/info/python/security/BinaryFileReader/MagicStrings.pyz
Project-URL: MagicStrings Windows Executable, https://mauricelambert.github.io/info/python/security/BinaryFileReader/MagicStrings.exe
Project-URL: Python Executable, https://mauricelambert.github.io/info/python/security/BinaryFileReader/BinaryFileReader.pyz
Project-URL: Python Windows Executable, https://mauricelambert.github.io/info/python/security/BinaryFileReader/BinaryFileReader.exe
Keywords: strings,hexadecimal,hexadecimal-reader,binary-file,reverse,binary-reader,binary-viewer
Platform: Windows
Platform: Linux
Platform: MacOS
Classifier: Topic :: System
Classifier: Topic :: Security
Classifier: Environment :: Console
Classifier: Operating System :: MacOS
Classifier: Operating System :: POSIX
Classifier: Topic :: System :: Shells
Classifier: Natural Language :: English
Classifier: Programming Language :: Python
Classifier: Intended Audience :: Developers
Classifier: Topic :: System :: System Shells
Classifier: Operating System :: POSIX :: Linux
Classifier: Programming Language :: Python :: 3.8
Classifier: Operating System :: Microsoft :: Windows
Classifier: Topic :: System :: Systems Administration
Classifier: Intended Audience :: System Administrators
Classifier: Development Status :: 5 - Production/Stable
Classifier: License :: OSI Approved :: GNU General Public License v3 or later (GPLv3+)
Requires-Python: >=3.8
License-File: LICENSE.txt
Requires-Dist: PythonToolsKit==1.2.4
Requires-Dist: PegParser>=1.1.4
Requires-Dist: RC4Encryption==0.0.2
Requires-Dist: RC6Encryption==1.0.1
Dynamic: author
Dynamic: download-url
Dynamic: home-page
Dynamic: maintainer
Dynamic: requires-python
